pyModbusTCP/__init__.py
pyModbusTCP/client.py
pyModbusTCP/constants.py
pyModbusTCP/server.py
pyModbusTCP/utils.py
pyModbusTCP-0.2.1.dist-info/LICENSE
pyModbusTCP-0.2.1.dist-info/METADATA
pyModbusTCP-0.2.1.dist-info/WHEEL
pyModbusTCP-0.2.1.dist-info/top_level.txt
pyModbusTCP-0.2.1.dist-info/RECORD
