Metadata-Version: 1.0
Name: pyModbusTCP
Version: 0.2.1
Summary: A simple Modbus/TCP library for Python
Home-page: https://github.com/sourceperl/pyModbusTCP
Author: Loic Lefebvre
Author-email: loic.celine@free.fr
License: MIT
Platform: any
